{
    "id": "11",
    "project": "Math",
    "git_url": "D4J",
    "docker_image": "defects4j:2.1.0",
    "bug_report": "https://issues.apache.org/jira/browse/MATH-929",
    "fix_commit": "aa2bd1d0656b0001192aa2b2ef779cfd1f3b7e4d",
    "build": "ant -Dd4j.project.id=Math compile",
    "build_test": "ant -Dd4j.project.id=Math compile.tests",
    "test_command": "ant -Dd4j.project.id=Math -Dtest.entry.class=org.apache.commons.math3.distribution.MultivariateNormalDistributionTest -Dtest.entry.method=testUnivariateDistribution run.dev.tests",
    "folder": "src/test/java/org/apache/commons/math3/distribution/",
    "file": "MultivariateNormalDistributionTest.java",
    "test_report": "target/surefire-reports/TEST-org.apache.commons.math3.distribution.MultivariateNormalDistributionTest.xml"
}